jupyterlab_export_markdown_extension/__init__.py
jupyterlab_export_markdown_extension/_version.py
jupyterlab_export_markdown_extension/routes.py
jupyterlab_export_markdown_extension/tests/__init__.py
jupyterlab_export_markdown_extension/tests/test_routes.py
jupyterlab_export_markdown_extension-1.1.12.data/data/etc/jupyter/jupyter_server_config.d/jupyterlab_export_markdown_extension.json
jupyterlab_export_markdown_extension-1.1.12.data/data/share/jupyter/labextensions/jupyterlab_export_markdown_extension/package.json
jupyterlab_export_markdown_extension-1.1.12.data/data/share/jupyter/labextensions/jupyterlab_export_markdown_extension/schemas/jupyterlab_export_markdown_extension/package.json.orig
jupyterlab_export_markdown_extension-1.1.12.data/data/share/jupyter/labextensions/jupyterlab_export_markdown_extension/schemas/jupyterlab_export_markdown_extension/plugin.json
jupyterlab_export_markdown_extension-1.1.12.data/data/share/jupyter/labextensions/jupyterlab_export_markdown_extension/static/728.9d5faa54a4332f0779ea.js
jupyterlab_export_markdown_extension-1.1.12.data/data/share/jupyter/labextensions/jupyterlab_export_markdown_extension/static/750.6d208721a17bb03bec46.js
jupyterlab_export_markdown_extension-1.1.12.data/data/share/jupyter/labextensions/jupyterlab_export_markdown_extension/static/remoteEntry.7df8ae62f17200d64391.js
jupyterlab_export_markdown_extension-1.1.12.data/data/share/jupyter/labextensions/jupyterlab_export_markdown_extension/static/style.js
jupyterlab_export_markdown_extension-1.1.12.data/data/share/jupyter/labextensions/jupyterlab_export_markdown_extension/static/third-party-licenses.json
jupyterlab_export_markdown_extension-1.1.12.data/data/share/jupyter/labextensions/jupyterlab_export_markdown_extension/install.json
jupyterlab_export_markdown_extension-1.1.12.dist-info/METADATA
jupyterlab_export_markdown_extension-1.1.12.dist-info/WHEEL
jupyterlab_export_markdown_extension-1.1.12.dist-info/licenses/LICENSE
jupyterlab_export_markdown_extension-1.1.12.dist-info/RECORD
