Metadata-Version: 2.4
Name: jupyterlab_export_markdown_extension
Version: 1.1.12
Summary: Jupyterlab extension to export markdown file as pdf, docx and html (with embedded images)
Project-URL: Homepage, https://github.com/stellarshenson/jupyterlab_export_markdown_extension
Project-URL: Bug Tracker, https://github.com/stellarshenson/jupyterlab_export_markdown_extension/issues
Project-URL: Repository, https://github.com/stellarshenson/jupyterlab_export_markdown_extension.git
Author-email: Stellars Henson <konrad.jelen@gmail.com>
License: BSD 3-Clause License
License-File: LICENSE
Keywords: jupyter,jupyterlab,jupyterlab-extension
Classifier: Framework :: Jupyter
Classifier: Framework :: Jupyter :: JupyterLab
Classifier: Framework :: Jupyter :: JupyterLab :: 4
Classifier: Framework :: Jupyter :: JupyterLab :: Extensions
Classifier: Framework :: Jupyter :: JupyterLab :: Extensions :: Prebuilt
Classifier: License :: OSI Approved :: BSD License
Classifier: Programming Language :: Python
Classifier: Programming Language :: Python :: 3
Classifier: Programming Language :: Python :: 3.9
Classifier: Programming Language :: Python :: 3.10
Classifier: Programming Language :: Python :: 3.11
Classifier: Programming Language :: Python :: 3.12
Classifier: Programming Language :: Python :: 3.13
Requires-Python: >=3.9
Requires-Dist: cairosvg>=2.7
Requires-Dist: htmldocx>=0.0.6
Requires-Dist: markdown>=3.4
Requires-Dist: python-docx>=1.0
Requires-Dist: reportlab>=4.0
Provides-Extra: dev
Requires-Dist: jupyterlab>=4; extra == 'dev'
Provides-Extra: test
Requires-Dist: coverage; extra == 'test'
Requires-Dist: pytest; extra == 'test'
Requires-Dist: pytest-asyncio; extra == 'test'
Requires-Dist: pytest-cov; extra == 'test'
Requires-Dist: pytest-jupyter[server]>=0.6.0; extra == 'test'
